[
  {
    "type": "request",
    "senderId": 0,
    "receiverId": 1,
    "postId": 0,
    "notificationMessage": " you have received a friend request from as",
    "id": 2,
    "isActive": false,
    "date": "Oct 29, 2022, 6:10:54 PM"
  },
  {
    "type": "post",
    "senderId": 0,
    "receiverId": 0,
    "postId": 5,
    "notificationMessage": "Your friend as put new post",
    "id": 6,
    "isActive": true,
    "date": "Oct 29, 2022, 6:11:45 PM"
  },
  {
    "type": "like",
    "senderId": 1,
    "receiverId": 0,
    "postId": 5,
    "notificationMessage": "sa liked your 5 post",
    "id": 22,
    "isActive": true,
    "date": "Oct 29, 2022, 6:36:38 PM"
  },
  {
    "type": "like",
    "senderId": 1,
    "receiverId": 0,
    "postId": 5,
    "notificationMessage": "sa liked your 5 post",
    "id": 23,
    "isActive": true,
    "date": "Oct 29, 2022, 6:36:44 PM"
  },
  {
    "type": "commit",
    "senderId": 1,
    "receiverId": 0,
    "postId": 5,
    "notificationMessage": "sa commited your 5 post",
    "id": 25,
    "isActive": true,
    "date": "Oct 29, 2022, 6:37:04 PM"
  },
  {
    "type": "like",
    "senderId": 1,
    "receiverId": 0,
    "postId": 5,
    "notificationMessage": "sa liked your 5 post",
    "id": 26,
    "isActive": true,
    "date": "Oct 29, 2022, 6:40:24 PM"
  },
  {
    "type": "like",
    "senderId": 1,
    "receiverId": 0,
    "postId": 5,
    "notificationMessage": "sa liked your 5 post",
    "id": 27,
    "isActive": true,
    "date": "Oct 29, 2022, 6:40:25 PM"
  },
  {
    "type": "like",
    "senderId": 1,
    "receiverId": 0,
    "postId": 5,
    "notificationMessage": "sa disliked your 5 post",
    "id": 32,
    "isActive": true,
    "date": "Oct 29, 2022, 6:45:31 PM"
  },
  {
    "type": "like",
    "senderId": 1,
    "receiverId": 0,
    "postId": 5,
    "notificationMessage": "sa Liked your 5 post",
    "id": 33,
    "isActive": true,
    "date": "Oct 29, 2022, 6:45:33 PM"
  },
  {
    "type": "like",
    "senderId": 1,
    "receiverId": 0,
    "postId": 5,
    "notificationMessage": "sa disliked your 5 post",
    "id": 34,
    "isActive": true,
    "date": "Oct 29, 2022, 6:45:36 PM"
  },
  {
    "type": "like",
    "senderId": 1,
    "receiverId": 0,
    "postId": 5,
    "notificationMessage": "sa Liked your 5 post",
    "id": 35,
    "isActive": true,
    "date": "Oct 29, 2022, 6:45:37 PM"
  },
  {
    "type": "post",
    "senderId": 1,
    "receiverId": 0,
    "postId": 46,
    "notificationMessage": "Your friend sa put new post",
    "id": 47,
    "isActive": true,
    "date": "Oct 29, 2022, 9:13:41 PM"
  },
  {
    "type": "commit",
    "senderId": 0,
    "receiverId": 1,
    "postId": 46,
    "notificationMessage": "as commited your 46 post",
    "id": 49,
    "isActive": true,
    "date": "Oct 29, 2022, 9:15:26 PM"
  },
  {
    "type": "post",
    "senderId": 0,
    "receiverId": 0,
    "postId": 51,
    "notificationMessage": "Your friend as put new post",
    "id": 52,
    "isActive": true,
    "date": "Oct 29, 2022, 9:16:30 PM"
  }
]